.gitignore
A-density-and-cumulative-histogram-of-x-2-are-plotted-on-the-same-plot.svg
Changes
Heat-map-pops-up-where-first-parabola-used-to-be.svg
LICENSE
MANIFEST.in
Makefile
README
README.footer.org
README.org
Same-histograms-but-plotted-on-two-separate-plots.svg
Two-3D-spirals-together-in-a-new-window.svg
basic-parabola-plot-pops-up.svg
extract_README.py
gnuplotlib.py
parabola-with-x-y-errobars-pops-up-in-a-new-window.svg
requirements.txt
setup.py
test.py
gnuplotlib.egg-info/PKG-INFO
gnuplotlib.egg-info/SOURCES.txt
gnuplotlib.egg-info/dependency_links.txt
gnuplotlib.egg-info/requires.txt
gnuplotlib.egg-info/top_level.txt
guide/.dir-locals.el
guide/gnuplot-terminal-test.svg
guide/guide-1.svg
guide/guide-10.svg
guide/guide-11.svg
guide/guide-13.svg
guide/guide-15.svg
guide/guide-16.svg
guide/guide-17.svg
guide/guide-18.svg
guide/guide-19.svg
guide/guide-2.svg
guide/guide-20.svg
guide/guide-21.svg
guide/guide-22.svg
guide/guide-23.svg
guide/guide-24.svg
guide/guide-25.svg
guide/guide-26.svg
guide/guide-27.svg
guide/guide-28.svg
guide/guide-29.svg
guide/guide-3.svg
guide/guide-30.svg
guide/guide-31.svg
guide/guide-32.svg
guide/guide-33.svg
guide/guide-34.svg
guide/guide-35.svg
guide/guide-36.svg
guide/guide-37.svg
guide/guide-38.svg
guide/guide-39.svg
guide/guide-4.svg
guide/guide-5.svg
guide/guide-7.svg
guide/guide.org