Metadata-Version: 2.2
Name: gnuplotlib
Version: 0.45
Summary: Gnuplot-based plotting for numpy
Home-page: http://github.com/dkogan/gnuplotlib
Author: Dima Kogan
Author-email: dima@secretsauce.net
License: LGPL
License-File: LICENSE
Requires-Dist: numpy
Requires-Dist: numpysane>=0.3
Dynamic: author
Dynamic: author-email
Dynamic: description
Dynamic: home-page
Dynamic: license
Dynamic: requires-dist
Dynamic: summary
